mockingmirror.py
mockingmirror-0.2.dist-info/top_level.txt
mockingmirror-0.2.dist-info/METADATA
mockingmirror-0.2.dist-info/DESCRIPTION.rst
mockingmirror-0.2.dist-info/metadata.json
mockingmirror-0.2.dist-info/WHEEL
mockingmirror-0.2.dist-info/RECORD
