Metadata-Version: 2.0
Name: mockingmirror
Version: 0.2
Summary: Make strict mocks using a mirror
Home-page: https://github.com/NegativeMjark/mockingmirror
Author: Mark Haines
Author-email: mjark@negativecurvature.net
License: Apache License, Version 2.0
Keywords: mock
Platform: UNKNOWN
Classifier: Development Status :: 3 - Alpha
Classifier: Intended Audience :: Developers
Classifier: License :: OSI Approved :: Apache Software License
Classifier: Programming Language :: Python :: 2
Requires-Dist: mock
